Tarea 1/Originales/opcodes.vh
// Modos de direccionamiento (addressing) (son parte del opcode [7:0], específicamente los bits [2:0])
`define DIRECC_IMP    'b000  // Direccionamiento implícito o no necesario para la operación
`define DIRECC_INM    'b001  // Direccionamiento inmediato
`define DIRECC_REG    'b010  // Direccionamiento de registros
`define DIRECC_DIRECT 'b011  // Direccionamiento directo
`define DIRECC_INDREG 'b100  // Direccionamiento indirecto por registros

// Opcodes

// Opcodes especiales
`define OP_NOP        'b00000  // (0x00) Ningúna Operación (hace nada, No Op)
`define OP_HLT        'b11111  // (0x1F) Halt. Detiene la máquina/CPU
// Memoria
`define OP_LD         'b00001  // (0x01)
`define OP_STR        'b00010  // (0x02)
// Lógicas
`define OP_NOT        'b10000  // (0x10)
`define OP_AND        'b10001  // (0x11)
`define OP_OR         'b10010  // (0x12)
`define OP_XOR        'b10011  // (0x13)
// Aritméticas
`define OP_NEG        'b10100  // (0x14)
`define OP_ADD        'b10101  // (0x15)
`define OP_SUB        'b10110  // (0x16)
`define OP_MUL        'b10111  // (0x17)
`define OP_DIV        'b11000  // (0x18)
`define OP_MOD        'b11001  // (0x19)
// Control
`define OP_JMP        'b11010  // (0x1A)
`define OP_JC         'b11011  // (0x1B)
`define OP_JS         'b11100  // (0x1C)
`define OP_JO         'b11101  // (0x1D)
`define OP_JZ         'b11110  // (0x1E)

// Combinaciones válidas de Opcodes y Direccionamiento

// Opcodes especiales
`define OPD_NOP        'b00000_000  // (0x00) Ningúna Operación (hace nada, No Op)
`define OPD_HLT        'b11111_000  // (0xF8) Halt. Detiene la máquina/CPU
// Memoria
// (Para el load, el destino siempre es un registro. La fuente puede variar dependiendo del modo de direccionamiento)
`define OPD_LD_INM     'b00001_001  // (0x09) Carga un valor inmediato al registro. Ya que el valor inmediato son 16 bits y el registro 32 bits, se hará extensión de signo
`define OPD_LD_REG     'b00001_010  // (0x0A) Load entre registros. Permite mover fácilmente el valor de un Registro A a otro Registro B
`define OPD_LD_DIRECT  'b00001_011  // (0x0B)
`define OPD_LD_INDREG  'b00001_100  // (0x0C)
// (Para el store, la fuente siempre es un registro. El destino puede variar dependiendo del modo de direccionamiento)
`define OPD_STR_DIRECT 'b00010_011  // (0x13)
`define OPD_STR_INDREG 'b00010_100  // (0x14)
// Lógicas (Todas usa direccionamiento de registros únicamente)
`define OPD_NOT        'b10000_010  // (0x82)
`define OPD_AND        'b10001_010  // (0x86)
`define OPD_OR         'b10010_010  // (0x92)
`define OPD_XOR        'b10011_010  // (0x96)
// Aritméticas (Todas usa direccionamiento de registros únicamente)
`define OPD_NEG        'b10100_010  // (0xA2)
`define OPD_ADD        'b10101_010  // (0xA6)
`define OPD_SUB        'b10110_010  // (0xB2)
`define OPD_MUL        'b10111_010  // (0xB6)
`define OPD_DIV        'b11000_010  // (0xC2)
`define OPD_MOD        'b11001_010  // (0xC6)
// Control (Todas son saltos absolutos, y usan direccionamiento inmediato únicamente)
`define OPD_JMP        'b11010_001  // (0xD1)
`define OPD_JC         'b11011_001  // (0xD9)
`define OPD_JS         'b11100_001  // (0xE1)
`define OPD_JO         'b11101_001  // (0xE9)
`define OPD_JZ         'b11110_001  // (0xF1)

// Para ver los opcodes con nombres en GTKWave
// https://electronics.stackexchange.com/questions/530123/viewing-verilog-enums-in-iverilog-gtkwave

// Create a file with the extension gtkw. This file contains how you want the state variable to be displayed on
// the waveform. For your example it would be:
//
// 00 STATE0
// 01 STATE1
// 10 STATE2
//
// Because you have used logic type which is 2 bits wide and have not encoded the state variables, SystemVerilog
// assigns the state variables the default values in ascending order. In this case the default binary values would
// be from 00 to 10 since you have 3 State variables.
// 
// Open the waveform and dump the signal. Do  Right-Mouse -> Data Format -> Translate Filter File -> Enable and Select.
// The Select Signal Filter Dialog Box opens. Then left click on Add Filter to List button. Select the gtkw extension file
// that you created. This file will then be displayed in the Select Signal Filter dialog box. Select your file in the Select
// Filter Dialog Box, make sure it is highlighted, then left click on the OK button. The binary signals in the waveform should
// be replaced with the enum values.

ProyectoFinal/alu.v
/*******************************
Universidad de Costa Rica
CI-0114: Fundamentos de Arquitectura

Modulo de una ALU combinacional,
parcialmente implementada

*********************************/

`include "opcodes.vh"

module ALU(resultado, C, S, O, Z, operando_a, operando_b, opcode);
  parameter BITS_DATA = 32;

  output reg [BITS_DATA-1:0] resultado;
  output reg C;
  output reg S;
  output reg O;
  output reg Z;

  input [BITS_DATA-1:0] operando_a;
  input [BITS_DATA-1:0] operando_b;
  input [4:0] opcode;
  
  // Con el @*, estamos definiendo un bloque combinacional
  // ya que no depende de ningún reloj
  // La lógica combinacional debe usar asignación bloqueante
  always @* begin
    case (opcode)
	
      `OP_NOT: begin
        resultado = ~operando_a;
        C = 0;
        S = resultado[BITS_DATA-1];
        O = 0;
        Z = ~(|resultado);
      end
	  
	  `OP_AND: begin
        resultado = operando_a & operando_b;
        C = 0;
        S = resultado[BITS_DATA-1];
        O = 0;
        Z = ~(|resultado);
      end
	  
	  `OP_OR: begin
        resultado = operando_a | operando_b;
        C = 0;
        S = resultado[BITS_DATA-1];
        O = 0;
        Z = ~(|resultado);
      end
	  
	  `OP_NEG: begin
        resultado = -operando_a;
        C = 0;
        S = resultado[BITS_DATA-1];
        O = 0;
        Z = ~(|resultado);
      end

      `OP_ADD: begin
        {C,resultado} = operando_a + operando_b;
        S = resultado[BITS_DATA-1];
        // Overflow es 1 cuando hay cambio en el bit de signo. Solo
        // puedo ocurrir cuando los operandos tienen el mismo signo
        O = (operando_a[BITS_DATA-1] == operando_b[BITS_DATA-1]) &&
            (operando_a[BITS_DATA-1] !=  resultado[BITS_DATA-1]);
        Z = ~(|resultado);
      end
	  
	  `OP_SUB: begin
        {C,resultado} = ~operando_a - operando_b;
        S = resultado[BITS_DATA-1];
        O = (operando_a[BITS_DATA-1] == operando_b[BITS_DATA-1]) &&
            (operando_a[BITS_DATA-1] !=  resultado[BITS_DATA-1]);
        Z = ~(|resultado);
      end
	  
	  `OP_MUL: begin
        {C,resultado} = operando_a * operando_b;
        S = resultado[BITS_DATA-1];
        O = (operando_a[BITS_DATA-1] == operando_b[BITS_DATA-1]) &&
            (operando_a[BITS_DATA-1] !=  resultado[BITS_DATA-1]);
        Z = ~(|resultado);
      end
	  
	  `OP_LD: begin
        resultado = ~operando_a;
        C = 0;
        S = resultado[BITS_DATA-1];
        O = 0;
        Z = ~(|resultado);
      end
	  
	  `OP_STR: begin
        resultado = ~operando_a;
        C = 0;
        S = resultado[BITS_DATA-1];
        O = 0;
        Z = ~(|resultado);
      end
	  
	  `OP_JZ: begin
        resultado = ~operando_a;
        C = 0;
        S = resultado[BITS_DATA-1];
        O = 0;
        Z = ~(|resultado);
      end
	  
	  `OP_JMP: begin
        resultado = ~operando_a;
        C = 0;
        S = resultado[BITS_DATA-1];
        O = 0;
        Z = ~(|resultado);
      end

      default: begin
        // El opcode no esta implementado o bien no es un
        // opcode de ALU valido. Intencionalmente propagaremos
        // Xs (indeterminado) a las salidas 
        resultado = 'hXXXX_XXXX;
        C = 'bx;
        S = 'bx;
        O = 'bx;
        Z = 'bx;
      end
    endcase
  end

endmodule

ProyectoFinal/alu_tb.v
/*******************************
Universidad de Costa Rica
CI-0114: Fundamentos de Arquitectura

Prueba para la ALU
*********************************/

`timescale 1us/100ns

module ALU_tb;
  wire [31:0] R;
  wire C, S, O, Z;
  reg  [31:0] A;
  reg  [31:0] B;
  reg  [4:0]  op;
 
  initial begin
    $dumpfile("ALU.vcd");
    $dumpvars;
    op = `OP_NOP; A = 0; B = 0;
    #1 op = `OP_LD; A = 32'h0000_0000; B = 32'h0000_000C;
	#1 op = `OP_LD; A = 32'h0000_0001; B = 32'h0000_0001;
	#1 op = `OP_LD; A = 32'h0000_0002; B = 32'h8000_0001;
	#1 op = `OP_LD; A = 32'h0000_0003; B = 32'h8000_0002;
    #1 op = `OP_MUL; A = 32'h0000_0001; B = 32'h8000_0002;
    #1 op = `OP_ADD; A = 32'h8000_0002; B = 32'h8000_0001;
	#1 op = `OP_JZ; A = 32'h8000_0000; B = 32'h8000_0000;
	#1 op = `OP_JMP; A = 32'h8000_0000; B = 32'h8000_0000;
	#1 op = `OP_MUL; A = 32'h0000_0001; B = 32'h8000_0002;
    #1 op = `OP_ADD; A = 32'h8000_0002; B = 32'h8000_0001;
	#1 op = `OP_MUL; A = 32'h0000_0002; B = 32'h8000_0003;
    #1 op = `OP_ADD; A = 32'h8000_0002; B = 32'h8000_0001;
	#1 op = `OP_MUL; A = 32'h0000_0006; B = 32'h0000_0004;
    #1 op = `OP_ADD; A = 32'h8000_0002; B = 32'h8000_0001;
	#1 op = `OP_MUL; A = 32'h0000_0018; B = 32'h0000_0005;
    #1 op = `OP_ADD; A = 32'h8000_0002; B = 32'h8000_0001;
	#1 op = `OP_MUL; A = 32'h0000_0078; B = 32'h0000_0006;
    #1 op = `OP_ADD; A = 32'h8000_0002; B = 32'h8000_0001;
	#1 op = `OP_MUL; A = 32'h0000_02D0; B = 32'h0000_0007;
    #1 op = `OP_ADD; A = 32'h8000_0002; B = 32'h8000_0001;
	#1 op = `OP_MUL; A = 32'h0000_13B0; B = 32'h0000_0008;
    #1 op = `OP_ADD; A = 32'h8000_0002; B = 32'h8000_0001;
	#1 op = `OP_MUL; A = 32'h0000_9D80; B = 32'h0000_0009;
    #1 op = `OP_ADD; A = 32'h8000_0002; B = 32'h8000_0001;
	#1 op = `OP_MUL; A = 32'h0005_8980; B = 32'h0000_000A;
    #1 op = `OP_ADD; A = 32'h8000_0002; B = 32'h8000_0001;
	#1 op = `OP_MUL; A = 32'h0037_5F00; B = 32'h0000_000B;
    #1 op = `OP_ADD; A = 32'h8000_0002; B = 32'h8000_0001;
	#1 op = `OP_STR; A = 32'h8000_0000; B = 32'h8000_0000;
	#1 op = `OP_MUL; A = 32'h0261_1500; B = 32'h0000_000C;
    #1 $finish;
  end
  
  ALU alu(.resultado(R),
          .C(C),
          .S(S),
          .O(O),
          .Z(Z),
          .operando_a(A),
          .operando_b(B),
          .opcode(op));
	

endmodule

ProyectoFinal/ALU.vcd
$date
	Tue Jul 19 03:26:50 2022
$end
$version
	Icarus Verilog
$end
$timescale
	100ns
$end
$scope module ALU_tb $end
$var wire 1 ! Z $end
$var wire 1 " S $end
$var wire 32 # R [31:0] $end
$var wire 1 $ O $end
$var wire 1 % C $end
$var reg 32 & A [31:0] $end
$var reg 32 ' B [31:0] $end
$var reg 5 ( op [4:0] $end
$scope module alu $end
$var wire 5 ) opcode [4:0] $end
$var wire 32 * operando_a [31:0] $end
$var wire 32 + operando_b [31:0] $end
$var reg 1 % C $end
$var reg 1 $ O $end
$var reg 1 " S $end
$var reg 1 ! Z $end
$var reg 32 , resultado [31:0] $end
$upscope $end
$upscope $end
$enddefinitions $end
#0
$dumpvars
bx ,
b0 +
b0 *
b0 )
b0 (
b0 '
b0 &
x%
x$
bx #
x"
x!
$end
#10
0!
0$
1"
0%
b11111111111111111111111111111111 #
b11111111111111111111111111111111 ,
b1100 '
b1100 +
b1 (
b1 )
#20
b11111111111111111111111111111110 #
b11111111111111111111111111111110 ,
b1 '
b1 +
b1 &
b1 *
#30
b11111111111111111111111111111101 #
b11111111111111111111111111111101 ,
b10000000000000000000000000000001 '
b10000000000000000000000000000001 +
b10 &
b10 *
#40
b11111111111111111111111111111100 #
b11111111111111111111111111111100 ,
b10000000000000000000000000000010 '
b10000000000000000000000000000010 +
b11 &
b11 *
#50
b10000000000000000000000000000010 #
b10000000000000000000000000000010 ,
b1 &
b1 *
b10111 (
b10111 )
#60
1$
0"
1%
b11 #
b11 ,
b10000000000000000000000000000001 '
b10000000000000000000000000000001 +
b10000000000000000000000000000010 &
b10000000000000000000000000000010 *
b10101 (
b10101 )
#70
0$
0%
b1111111111111111111111111111111 #
b1111111111111111111111111111111 ,
b10000000000000000000000000000000 '
b10000000000000000000000000000000 +
b10000000000000000000000000000000 &
b10000000000000000000000000000000 *
b11110 (
b11110 )
#80
b11010 (
b11010 )
#90
1"
b10000000000000000000000000000010 #
b10000000000000000000000000000010 ,
b10000000000000000000000000000010 '
b10000000000000000000000000000010 +
b1 &
b1 *
b10111 (
b10111 )
#100
1$
0"
1%
b11 #
b11 ,
b10000000000000000000000000000001 '
b10000000000000000000000000000001 +
b10000000000000000000000000000010 &
b10000000000000000000000000000010 *
b10101 (
b10101 )
#110
0$
b110 #
b110 ,
b10000000000000000000000000000011 '
b10000000000000000000000000000011 +
b10 &
b10 *
b10111 (
b10111 )
#120
1$
b11 #
b11 ,
b10000000000000000000000000000001 '
b10000000000000000000000000000001 +
b10000000000000000000000000000010 &
b10000000000000000000000000000010 *
b10101 (
b10101 )
#130
0$
0%
b11000 #
b11000 ,
b100 '
b100 +
b110 &
b110 *
b10111 (
b10111 )
#140
1$
1%
b11 #
b11 ,
b10000000000000000000000000000001 '
b10000000000000000000000000000001 +
b10000000000000000000000000000010 &
b10000000000000000000000000000010 *
b10101 (
b10101 )
#150
0$
0%
b1111000 #
b1111000 ,
b101 '
b101 +
b11000 &
b11000 *
b10111 (
b10111 )
#160
1$
1%
b11 #
b11 ,
b10000000000000000000000000000001 '
b10000000000000000000000000000001 +
b10000000000000000000000000000010 &
b10000000000000000000000000000010 *
b10101 (
b10101 )
#170
0$
0%
b1011010000 #
b1011010000 ,
b110 '
b110 +
b1111000 &
b1111000 *
b10111 (
b10111 )
#180
1$
1%
b11 #
b11 ,
b10000000000000000000000000000001 '
b10000000000000000000000000000001 +
b10000000000000000000000000000010 &
b10000000000000000000000000000010 *
b10101 (
b10101 )
#190
0$
0%
b1001110110000 #
b1001110110000 ,
b111 '
b111 +
b1011010000 &
b1011010000 *
b10111 (
b10111 )
#200
1$
1%
b11 #
b11 ,
b10000000000000000000000000000001 '
b10000000000000000000000000000001 +
b10000000000000000000000000000010 &
b10000000000000000000000000000010 *
b10101 (
b10101 )
#210
0$
0%
b1001110110000000 #
b1001110110000000 ,
b1000 '
b1000 +
b1001110110000 &
b1001110110000 *
b10111 (
b10111 )
#220
1$
1%
b11 #
b11 ,
b10000000000000000000000000000001 '
b10000000000000000000000000000001 +
b10000000000000000000000000000010 &
b10000000000000000000000000000010 *
b10101 (
b10101 )
#230
0$
0%
b1011000100110000000 #
b1011000100110000000 ,
b1001 '
b1001 +
b1001110110000000 &
b1001110110000000 *
b10111 (
b10111 )
#240
1$
1%
b11 #
b11 ,
b10000000000000000000000000000001 '
b10000000000000000000000000000001 +
b10000000000000000000000000000010 &
b10000000000000000000000000000010 *
b10101 (
b10101 )
#250
0$
0%
b1101110101111100000000 #
b1101110101111100000000 ,
b1010 '
b1010 +
b1011000100110000000 &
b1011000100110000000 *
b10111 (
b10111 )
#260
1$
1%
b11 #
b11 ,
b10000000000000000000000000000001 '
b10000000000000000000000000000001 +
b10000000000000000000000000000010 &
b10000000000000000000000000000010 *
b10101 (
b10101 )
#270
0$
0%
b10011000010001010100000000 #
b10011000010001010100000000 ,
b1011 '
b1011 +
b1101110101111100000000 &
b1101110101111100000000 *
b10111 (
b10111 )
#280
1$
1%
b11 #
b11 ,
b10000000000000000000000000000001 '
b10000000000000000000000000000001 +
b10000000000000000000000000000010 &
b10000000000000000000000000000010 *
b10101 (
b10101 )
#290
0$
0%
b1111111111111111111111111111111 #
b1111111111111111111111111111111 ,
b10000000000000000000000000000000 '
b10000000000000000000000000000000 +
b10000000000000000000000000000000 &
b10000000000000000000000000000000 *
b10 (
b10 )
#300
b11100100011001111110000000000 #
b11100100011001111110000000000 ,
b1100 '
b1100 +
b10011000010001010100000000 &
b10011000010001010100000000 *
b10111 (
b10111 )
