Tarea 0/maquina_RTL.v
/*******************************
Eiran Amador Alvarado C00411
Fundamentos de Arquitectura
Tarea 0

Archivo .v con la implementación del módulo que define la máquina de estados
********************************/

module Ganar_3_de_5_RTL(EST, V_J1G3, V_J2G3, E_G3, ERR_11, J1G, J2G, Reset, clk);
  
  output reg [3:0] EST = 0;

  output reg [1:0] V_J1G3;
  output reg [1:0] V_J2G3;
  output reg [1:0] E_G3;
  output reg [1:0] ERR_11;

  input J1G, J2G, Reset, clk;

  always @(negedge clk or Reset) begin
    
    if (Reset) begin
        EST = 0;
        ERR_11 = 0;
        V_J1G3 = 0;
        V_J2G3 = 0;
        E_G3 = 0;
    end
  
    case (EST)
      0: begin//J1G0_J2G0
        if (J1G && J2G) begin EST = 9; end
        else if (J1G) begin EST = 1; end
        else if (J2G) begin EST = 2; end
      end

      1: begin//J1G1_J2G0
        if (J1G && J2G) begin EST = 9; end
        else if (J1G) begin EST = 4; end
        else if (J2G) begin EST = 3; end
      end

      2: begin//J1G0_J2G1
        if (J1G && J2G) begin EST = 9; end
        else if (J1G) begin EST = 3; end
        else if (J2G) begin EST = 7; end
      end

      3: begin//J1G1_J2G1
        if (J1G && J2G) begin EST = 9; end
        else if (J1G) begin EST = 3; end
        else if (J2G) begin EST = 2; end
      end

      4: begin//J1G2_J2G0
        if (J1G && J2G) begin EST = 9; end
        else if (J1G) begin EST = 12; end//J1 Gana 3:0
        else if (J2G) begin EST = 5; end
      end

      5: begin//J1G2_J2G1
        if (J1G && J2G) begin EST = 9; end
        else if (J1G) begin EST = 10; end//J1 Gana
        else if (J2G) begin EST = 8; end
      end

      6: begin//J1G1_J2G2
        if (J1G && J2G) begin EST = 9; end
        else if (J1G) begin EST = 8; end
        else if (J2G) begin EST = 11; V_J2G3 = 1; end//J2 Gana
      end

      7: begin//J1G0_J2G2
        if (J1G && J2G) begin EST = 9; end
        else if (J1G) begin EST = 6; end
        else if (J2G) begin EST = 13;  end//J2 Gana 3:0
      end

      8: begin//J1G2_J2G2
        if (J1G && J2G) begin EST = 9; end
        else if (J1G) begin EST = 10; end//J1 Gana
        else if (J2G) begin EST = 11; end//J2 Gana
      end
	
      9: begin//Estado ERR_11 
        EST = 9; ERR_11 = 1;
      end

      10: begin//V_J1G3
        EST = 10; V_J1G3 = 1;
      end

      11: begin//V_J2G3
        EST = 11; V_J2G3 = 1;
      end

      12: begin//V_J1G3 E_G3
        EST = 12; V_J1G3 = 1; E_G3 = 1; 
      end

      13: begin//V_J2G3 E_G3
        EST = 13; V_J2G3 = 1; E_G3 = 1;
      end
    endcase

  end
endmodule

Tarea 0/maquina_RLT_tb.v
/*******************************
Eiran Amador Alvarado C00411
Fundamentos de Arquitectura
Tarea 0

Archivo .v con el testbench que instancia la máquina de estados y aplica los estímulos de
prueba requeridos
********************************/

`timescale 1us/100ns

module Ganar_3_de_5_RTL_tb;
  reg Clk, Reset;
  reg J1G, J2G;
  wire [3:0] EST;
  wire [1:0] V_J1G3;
  wire [1:0] V_J2G3;
  wire [1:0] E_G3;
  wire [1:0] ERR_11;
  always begin
    #0.5 Clk = ~Clk;
  end
  
  initial begin
    $dumpfile("maquina.vcd");
    $dumpvars;

    $monitor($time, "us : " , "clk %b, J1G %b, J2G %b, V_J1G3 %b, V_J2G3 %b, E_G3 %b , ERR_11 %b, EST %d", Clk, J1G, J2G, V_J1G3, V_J2G3, E_G3, ERR_11, EST);
    Clk = 1; J1G = 0; J2G = 0; Reset = 0;
    #1 Reset = 1;
    #1 Reset = 0;
    #1 J1G = 1; J2G = 0;
    #1 J1G = 0; J2G = 0;
    #1 J1G = 1; J2G = 0;
    #1 J1G = 0; J2G = 0;
    #1 J1G = 1; J2G = 0;//El jugador 1 gana 3:0
    #1 J1G = 0; J2G = 0;
    #1 Reset = 1;
    #1 Reset = 0;
    #1 J1G = 0; J2G = 1;
    #1 J1G = 0; J2G = 0;
    #1 J1G = 0; J2G = 1;
    #1 J1G = 0; J2G = 0;
    #1 J1G = 0; J2G = 1;//El jugador 2 gana 3:0
    #1 J1G = 0; J2G = 0;
    #1 Reset = 1;
    #1 Reset = 0;
    #1 J1G = 1; J2G = 0;
    #1 J1G = 1; J2G = 0;
    #1 J1G = 0; J2G = 1;
    #1 J1G = 0; J2G = 1;
    #1 J1G = 1; J2G = 0;//El jugador 1 gana 3:2
    #1 J1G = 0; J2G = 0;
    #1 Reset = 1;
    #1 Reset = 0;
    #1 J1G = 0; J2G = 1;
    #1 J1G = 0; J2G = 1;
    #1 J1G = 1; J2G = 0;
    #1 J1G = 0; J2G = 1;//El jugador 2 gana 3:1
    #1 J1G = 0; J2G = 0;
    #1 Reset = 1;
    #1 Reset = 0;
    #1 J1G = 1; J2G = 1;//Error
    #1 J1G = 1; J2G = 1;
    #1 J1G = 1; J2G = 1;
    #10 $finish;
  end
  
  Ganar_3_de_5_RTL maquina(EST, V_J1G3, V_J2G3, E_G3, ERR_11, J1G, J2G, Reset, Clk);
endmodule

Tarea 0/maquina.vcd
$date
	Fri May 20 17:55:21 2022
$end
$version
	Icarus Verilog
$end
$timescale
	100ns
$end
$scope module Ganar_3_de_5_RTL_tb $end
$var wire 2 ! V_J2G3 [1:0] $end
$var wire 2 " V_J1G3 [1:0] $end
$var wire 2 # E_G3 [1:0] $end
$var wire 4 $ EST [3:0] $end
$var wire 2 % ERR_11 [1:0] $end
$var reg 1 & Clk $end
$var reg 1 ' J1G $end
$var reg 1 ( J2G $end
$var reg 1 ) Reset $end
$scope module maquina $end
$var wire 1 ' J1G $end
$var wire 1 ( J2G $end
$var wire 1 ) Reset $end
$var wire 1 & clk $end
$var reg 2 * ERR_11 [1:0] $end
$var reg 4 + EST [3:0] $end
$var reg 2 , E_G3 [1:0] $end
$var reg 2 - V_J1G3 [1:0] $end
$var reg 2 . V_J2G3 [1:0] $end
$upscope $end
$upscope $end
$enddefinitions $end
#0
$dumpvars
bx .
bx -
bx ,
b0 +
bx *
0)
0(
0'
1&
bx %
b0 $
bx #
bx "
bx !
$end
#5
0&
#10
b0 #
b0 ,
b0 !
b0 .
b0 "
b0 -
b0 %
b0 *
1&
1)
#15
0&
#20
1&
0)
#25
0&
#30
1&
1'
#35
b1 $
b1 +
0&
#40
1&
0'
#45
0&
#50
1&
1'
#55
b100 $
b100 +
0&
#60
1&
0'
#65
0&
#70
1&
1'
#75
b1100 $
b1100 +
0&
#80
1&
0'
#85
b1 #
b1 ,
b1 "
b1 -
0&
#90
b0 #
b0 ,
b0 "
b0 -
b0 $
b0 +
1&
1)
#95
0&
#100
1&
0)
#105
0&
#110
1&
1(
#115
b10 $
b10 +
0&
#120
1&
0(
#125
0&
#130
1&
1(
#135
b111 $
b111 +
0&
#140
1&
0(
#145
0&
#150
1&
1(
#155
b1101 $
b1101 +
0&
#160
1&
0(
#165
b1 #
b1 ,
b1 !
b1 .
0&
#170
b0 #
b0 ,
b0 !
b0 .
b0 $
b0 +
1&
1)
#175
0&
#180
1&
0)
#185
0&
#190
1&
1'
#195
b1 $
b1 +
0&
#200
1&
#205
b100 $
b100 +
0&
#210
1&
1(
0'
#215
b101 $
b101 +
0&
#220
1&
#225
b1000 $
b1000 +
0&
#230
1&
0(
1'
#235
b1010 $
b1010 +
0&
#240
1&
0'
#245
b1 "
b1 -
0&
#250
b0 "
b0 -
b0 $
b0 +
1&
1)
#255
0&
#260
1&
0)
#265
0&
#270
1&
1(
#275
b10 $
b10 +
0&
#280
1&
#285
b111 $
b111 +
0&
#290
1&
0(
1'
#295
b110 $
b110 +
0&
#300
1&
1(
0'
#305
b1 !
b1 .
b1011 $
b1011 +
0&
#310
1&
0(
#315
0&
#320
b0 !
b0 .
b0 $
b0 +
1&
1)
#325
0&
#330
1&
0)
#335
0&
#340
1&
1(
1'
#345
b1001 $
b1001 +
0&
#350
1&
#355
b1 %
b1 *
0&
